pandasglue/__init__.py
pandasglue/__version__.py
pandasglue/exceptions.py
pandasglue/read.py
pandasglue/write.py
pandasglue/services/__init__.py
pandasglue/services/base.py
pandasglue/services/glue.py
pandasglue/services/s3.py
pandasglue/writers/__init__.py
pandasglue/writers/base.py
pandasglue/writers/csv.py
pandasglue/writers/json.py
pandasglue/writers/parquet.py
pandasglue-0.0.3.dist-info/LICENSE
pandasglue-0.0.3.dist-info/METADATA
pandasglue-0.0.3.dist-info/WHEEL
pandasglue-0.0.3.dist-info/top_level.txt
pandasglue-0.0.3.dist-info/RECORD
