Metadata-Version: 2.1
Name: pandasglue
Version: 0.0.3
Summary: Productivity for your AWS Data Lake
Home-page: UNKNOWN
License: Apache License 2.0
Platform: UNKNOWN
Requires-Python: >=2.7
Requires-Dist: pyarrow (==0.12.0)
Requires-Dist: pandas (==0.24.1)
Requires-Dist: boto3
Requires-Dist: s3fs (==0.2.0)
